odoo10_addon_stock_location_lockdown-10.0.1.1.0-py2.7-nspkg.pth
odoo/addons/stock_location_lockdown/README.rst
odoo/addons/stock_location_lockdown/__init__.py
odoo/addons/stock_location_lockdown/__manifest__.py
odoo/addons/stock_location_lockdown/i18n/fr.po
odoo/addons/stock_location_lockdown/i18n/pt.po
odoo/addons/stock_location_lockdown/i18n/stock_location_lockdown.pot
odoo/addons/stock_location_lockdown/models/__init__.py
odoo/addons/stock_location_lockdown/models/stock_location.py
odoo/addons/stock_location_lockdown/models/stock_quant.py
odoo/addons/stock_location_lockdown/readme/CONTRIBUTORS.rst
odoo/addons/stock_location_lockdown/readme/DESCRIPTION.rst
odoo/addons/stock_location_lockdown/readme/USAGE.rst
odoo/addons/stock_location_lockdown/static/description/icon.png
odoo/addons/stock_location_lockdown/static/description/index.html
odoo/addons/stock_location_lockdown/tests/__init__.py
odoo/addons/stock_location_lockdown/tests/test_block_stock_location_entrance.py
odoo/addons/stock_location_lockdown/views/stock_location.xml
odoo10_addon_stock_location_lockdown-10.0.1.1.0.dist-info/METADATA
odoo10_addon_stock_location_lockdown-10.0.1.1.0.dist-info/RECORD
odoo10_addon_stock_location_lockdown-10.0.1.1.0.dist-info/WHEEL
odoo10_addon_stock_location_lockdown-10.0.1.1.0.dist-info/namespace_packages.txt
odoo10_addon_stock_location_lockdown-10.0.1.1.0.dist-info/top_level.txt
